signingscript/__init__.py
signingscript/createprecomplete.py
signingscript/exceptions.py
signingscript/script.py
signingscript/sign.py
signingscript/task.py
signingscript/utils.py
signingscript/data/host.cert
signingscript/data/signing_task_schema.json
signingscript/test/__init__.py
signingscript/test/example_server_config.json
signingscript/test/test_exceptions.py
signingscript/test/test_script.py
signingscript/test/test_sign.py
signingscript/test/test_task.py
signingscript/test/test_utils.py
signingscript/test/data/app.apk
signingscript/test/data/autograph_apk.pub
signingscript/test/data/autograph_mar.pub
signingscript/test/data/autograph_server_test_config.yaml
signingscript/test/data/id_rsa.pub
signingscript/test/data/partial1.mar
signingscript/test/data/partial2.mar
signingscript/test/data/test.tar.bz2
signingscript/test/data/test.tar.gz
signingscript/test/data/test.zip
signingscript/test/integration/__init__.py
signingscript/test/integration/test_autograph.py
signingscript-9.5.1.dist-info/DESCRIPTION.rst
signingscript-9.5.1.dist-info/METADATA
signingscript-9.5.1.dist-info/RECORD
signingscript-9.5.1.dist-info/WHEEL
signingscript-9.5.1.dist-info/entry_points.txt
signingscript-9.5.1.dist-info/metadata.json
signingscript-9.5.1.dist-info/top_level.txt
