Metadata-Version: 2.0
Name: signingscript
Version: 9.5.1
Summary: TaskCluster Signing Script
Home-page: https://github.com/mozilla-releng/signingscript
Author: Mozilla Release Engineering
Author-email: release+python@mozilla.com
License: MPL2
Platform: UNKNOWN
Requires-Dist: arrow
Requires-Dist: datadog
Requires-Dist: mar
Requires-Dist: python-jose
Requires-Dist: requests
Requires-Dist: requests-hawk
Requires-Dist: scriptworker
Requires-Dist: signtool
Requires-Dist: taskcluster
